dAbot/__init__.py
dAbot/__main__.py
dAbot/console.py
dAbot/dAbot.py
dAbot-2019.9.24.2.dist-info/LICENSE
dAbot-2019.9.24.2.dist-info/METADATA
dAbot-2019.9.24.2.dist-info/WHEEL
dAbot-2019.9.24.2.dist-info/entry_points.txt
dAbot-2019.9.24.2.dist-info/top_level.txt
dAbot-2019.9.24.2.dist-info/RECORD
