Metadata-Version: 2.1
Name: dAbot
Version: 2019.9.24.2
Summary: CLI tool to automate stuff on DeviantArt.com
Home-page: https://github.com/KishanBagaria/dAbot
Author: Kishan Bagaria
Author-email: hi@kishan.info
License: MIT
Download-URL: https://codeload.github.com/KishanBagaria/dAbot/tar.gz/master
Keywords: deviantart,llama,bot
Platform: UNKNOWN
Classifier: Development Status :: 3 - Alpha
Classifier: Environment :: Console
Classifier: License :: OSI Approved :: MIT License
Classifier: Programming Language :: Python :: 2.7
Requires-Dist: colorama
Requires-Dist: docopt
Requires-Dist: requests
Requires-Dist: retrying
Requires-Dist: PyYAML
Requires-Dist: python-dateutil
